StochasticProcessesLectureNotesUcbStat150/README.md
StochasticProcessesLectureNotesUcbStat150/__init__.py
StochasticProcessesLectureNotesUcbStat150/__main__.py
StochasticProcessesLectureNotesUcbStat150/file.pdf
StochasticProcessesLectureNotesUcbStat150/index.html
stochastic_processes_lecture_notes_ucb_stat150-2024.3.4.0.dist-info/METADATA
stochastic_processes_lecture_notes_ucb_stat150-2024.3.4.0.dist-info/WHEEL
stochastic_processes_lecture_notes_ucb_stat150-2024.3.4.0.dist-info/entry_points.txt
stochastic_processes_lecture_notes_ucb_stat150-2024.3.4.0.dist-info/top_level.txt
stochastic_processes_lecture_notes_ucb_stat150-2024.3.4.0.dist-info/RECORD
